README.md
setup.cfg
setup.py
winkrelayintercom.py
pywinkrelayintercom.egg-info/PKG-INFO
pywinkrelayintercom.egg-info/SOURCES.txt
pywinkrelayintercom.egg-info/dependency_links.txt
pywinkrelayintercom.egg-info/requires.txt
pywinkrelayintercom.egg-info/top_level.txt
pywinkrelayintercom.egg-info/zip-safe