Metadata-Version: 1.0
Name: pywinkrelayintercom
Version: 0.0.2
Summary: Python interface to broadcast audio to Wink Relay intercoms
Home-page: https://github.com/w1ll1am23/pywinkrelayintercom
Author: William Scanlon
Author-email: UNKNOWN
License: MIT
Platform: UNKNOWN
